odoo/addons/purchase_discount/README.rst
odoo/addons/purchase_discount/__init__.py
odoo/addons/purchase_discount/__manifest__.py
odoo/addons/purchase_discount/i18n/de.po
odoo/addons/purchase_discount/i18n/el_GR.po
odoo/addons/purchase_discount/i18n/es.po
odoo/addons/purchase_discount/i18n/es_MX.po
odoo/addons/purchase_discount/i18n/fr.po
odoo/addons/purchase_discount/i18n/fr_CH.po
odoo/addons/purchase_discount/i18n/hr.po
odoo/addons/purchase_discount/i18n/it.po
odoo/addons/purchase_discount/i18n/nl.po
odoo/addons/purchase_discount/i18n/pt_BR.po
odoo/addons/purchase_discount/i18n/pt_PT.po
odoo/addons/purchase_discount/i18n/purchase_discount.pot
odoo/addons/purchase_discount/i18n/sl.po
odoo/addons/purchase_discount/images/purchase_discount.png
odoo/addons/purchase_discount/models/__init__.py
odoo/addons/purchase_discount/models/account_invoice.py
odoo/addons/purchase_discount/models/purchase_order.py
odoo/addons/purchase_discount/models/stock_move.py
odoo/addons/purchase_discount/report/__init__.py
odoo/addons/purchase_discount/report/purchase_report.py
odoo/addons/purchase_discount/static/description/icon.png
odoo/addons/purchase_discount/static/description/icon.svg
odoo/addons/purchase_discount/tests/__init__.py
odoo/addons/purchase_discount/tests/test_purchase_discount.py
odoo/addons/purchase_discount/views/purchase_discount_view.xml
odoo/addons/purchase_discount/views/report_purchaseorder.xml
odoo11_addon_purchase_discount-11.0.1.0.3.dist-info/METADATA
odoo11_addon_purchase_discount-11.0.1.0.3.dist-info/RECORD
odoo11_addon_purchase_discount-11.0.1.0.3.dist-info/WHEEL
odoo11_addon_purchase_discount-11.0.1.0.3.dist-info/top_level.txt
